tsdownsample-0.1.4.1.dist-info/METADATA
tsdownsample-0.1.4.1.dist-info/WHEEL
tsdownsample-0.1.4.1.dist-info/licenses/LICENSE
tsdownsample/_python/__init__.py
tsdownsample/_python/downsamplers.py
tsdownsample/__init__.py
tsdownsample/downsamplers.py
tsdownsample/downsampling_interface.py
tsdownsample/_rust/__init__.py
tsdownsample/_rust/_tsdownsample_rs.cpython-38-s390x-linux-gnu.so
tsdownsample-0.1.4.1.dist-info/RECORD
