Metadata-Version: 2.4
Name: tsdownsample
Version: 0.1.4.1
Classifier: Intended Audience :: Developers
Classifier: License :: OSI Approved :: MIT License
Classifier: Programming Language :: Python :: 3
Classifier: Programming Language :: Python :: 3.8
Classifier: Programming Language :: Python :: 3.9
Classifier: Programming Language :: Python :: 3.10
Classifier: Programming Language :: Python :: 3.11
Classifier: Programming Language :: Python :: 3.12
Classifier: Programming Language :: Python :: 3.13
Classifier: Operating System :: POSIX
Classifier: Operating System :: MacOS :: MacOS X
Classifier: Operating System :: Microsoft :: Windows
Requires-Dist: numpy
License-File: LICENSE
Summary: Time series downsampling in rust
Keywords: time series,downsampling,rust,data science,visualization
Author: Jeroen Van Der Donckt
License: MIT
Requires-Python: >=3.8
Project-URL: Homepage, https://github.com/predict-idlab/tsdownsample
Project-URL: Repository, https://github.com/predict-idlab/tsdownsample
